.travis.yml
LICENSE
MANIFEST.in
README.rst
dev-requirements.txt
requirements.txt
setup.cfg
setup.py
test.ini
bin/travis-build.bash
bin/travis-run.sh
ckanext/__init__.py
ckanext/rq/__init__.py
ckanext/rq/action.py
ckanext/rq/auth.py
ckanext/rq/cli.py
ckanext/rq/jobs.py
ckanext/rq/plugin.py
ckanext/rq/redis.py
ckanext/rq/schema.py
ckanext/rq/supervisor-ckan-worker.conf
ckanext/rq/fanstatic/.gitignore
ckanext/rq/i18n/.gitignore
ckanext/rq/public/.gitignore
ckanext/rq/templates/.gitignore
ckanext/rq/tests/__init__.py
ckanext/rq/tests/helpers.py
ckanext/rq/tests/test_action.py
ckanext/rq/tests/test_jobs.py
ckanext/rq/tests/test_plugin.py
ckanext_rq.egg-info/PKG-INFO
ckanext_rq.egg-info/SOURCES.txt
ckanext_rq.egg-info/dependency_links.txt
ckanext_rq.egg-info/entry_points.txt
ckanext_rq.egg-info/namespace_packages.txt
ckanext_rq.egg-info/pbr.json
ckanext_rq.egg-info/top_level.txt