Metadata-Version: 1.1
Name: ckanext-rq
Version: 0.1
Summary: Background jobs functionality for CKAN 2.6 and earlier
Home-page: https://github.com/ckan/ckanext-rq
Author: David Read
Author-email: david.read@hackneyworkshop.com
License: AGPL
Keywords: CKAN rq jobs
Platform: UNKNOWN
Classifier: Development Status :: 4 - Beta
Classifier: License :: OSI Approved :: GNU Affero General Public License v3 or later (AGPLv3+)
Classifier: Programming Language :: Python :: 2.7
